asebytes/__init__.py
asebytes/decode.py
asebytes/encode.py
asebytes/io.py
asebytes/metadata.py
asebytes-0.1.7.dist-info/WHEEL
asebytes-0.1.7.dist-info/METADATA
asebytes-0.1.7.dist-info/RECORD
