Metadata-Version: 2.3
Name: asebytes
Version: 0.1.7
Summary: LMDB-based storage for ASE.
Author: Fabian Zills
Author-email: Fabian Zills <fzills@icp.uni-stuttgart.de>
Requires-Dist: ase>=3.26.0
Requires-Dist: lmdb>=1.7.5
Requires-Dist: msgpack>=1.1.2
Requires-Dist: msgpack-numpy>=0.4.8
Requires-Python: >=3.11
Project-URL: Discord, https://discord.gg/7ncfwhsnm4
Project-URL: Releases, https://github.com/zincware/asebytes/releases
Project-URL: Repository, https://github.com/zincware/asebytes
